HISTORY.rst
LICENSE.rst
MANIFEST.in
Makefile
README.rst
setup.py
bin/pyjoint
docs/Makefile
docs/build/doctrees/environment.pickle
docs/build/doctrees/index.doctree
docs/build/html/.buildinfo
docs/build/html/genindex.html
docs/build/html/index.html
docs/build/html/objects.inv
docs/build/html/search.html
docs/build/html/searchindex.js
docs/build/html/_sources/index.txt
docs/build/html/_static/ajax-loader.gif
docs/build/html/_static/basic.css
docs/build/html/_static/comment-bright.png
docs/build/html/_static/comment-close.png
docs/build/html/_static/comment.png
docs/build/html/_static/default.css
docs/build/html/_static/doctools.js
docs/build/html/_static/down-pressed.png
docs/build/html/_static/down.png
docs/build/html/_static/file.png
docs/build/html/_static/jquery.js
docs/build/html/_static/minus.png
docs/build/html/_static/plus.png
docs/build/html/_static/pygments.css
docs/build/html/_static/searchtools.js
docs/build/html/_static/sidebar.js
docs/build/html/_static/underscore.js
docs/build/html/_static/up-pressed.png
docs/build/html/_static/up.png
docs/build/html/_static/websupport.js
docs/source/conf.py
docs/source/index.rst
pyjoint/__init__.py
pyjoint/__main__.py
pyjoint/__version__.py
pyjoint.egg-info/PKG-INFO
pyjoint.egg-info/SOURCES.txt
pyjoint.egg-info/dependency_links.txt
pyjoint.egg-info/requires.txt
pyjoint.egg-info/top_level.txt
pyjoint/core/__init__.py