Metadata-Version: 1.1
Name: pyjoint
Version: 0.0.dev
Summary: Compute miter and tilt angles to create polyhedrons.
Home-page: http://pyjoint.readthedocs.org
Author: Manuel Lopez
Author-email: jmlopez.rod@gmail.com
License: BSD License
Keywords: pyjoint miter tilt angles templates
Platform: UNKNOWN
Classifier: Development Status :: 2 - Pre-Alpha
Classifier: License :: OSI Approved :: BSD License
Classifier: Operating System :: MacOS :: MacOS X
Classifier: Operating System :: POSIX :: Linux
Classifier: Programming Language :: Python
Classifier: Programming Language :: Python :: 2.7
Classifier: Topic :: Scientific/Engineering :: Mathematics
Classifier: Topic :: Scientific/Engineering :: Visualization
